xtlsapi/__init__.py
xtlsapi/__main__.py
xtlsapi/base.py
xtlsapi/cli.py
xtlsapi/generate_from_xray_proto.py
xtlsapi/api_services/__init__.py
xtlsapi/api_services/_base.py
xtlsapi/api_services/handler/__init__.py
xtlsapi/api_services/handler/add_client.py
xtlsapi/api_services/handler/remove_client.py
xtlsapi/api_services/logger/__init__.py
xtlsapi/api_services/logger/restart_logger.py
xtlsapi/api_services/stats/__init__.py
xtlsapi/api_services/stats/get_client_download_traffic.py
xtlsapi/api_services/stats/get_client_upload_traffic.py
xtlsapi/api_services/stats/get_inbound_download_traffic.py
xtlsapi/api_services/stats/get_inbound_upload_traffic.py
xtlsapi/api_services/stats/get_statsonline.py
xtlsapi/api_services/stats/get_statsquery.py
xtlsapi/api_services/stats/get_total_download_traffic.py
xtlsapi/api_services/stats/get_total_upload_traffic.py
xtlsapi/client/SingboxClient.py
xtlsapi/client/XrayClient.py
xtlsapi/client/__init__.py
xtlsapi/exceptions/__init__.py
xtlsapi/exceptions/_base.py
xtlsapi/exceptions/email_already_exists.py
xtlsapi/exceptions/email_not_found.py
xtlsapi/exceptions/inbound_not_found.py
xtlsapi/ext/__init__.py
xtlsapi/ext/utils.py
xtlsapi/singbox_api/__init__.py
xtlsapi/singbox_api/extensions_pb2.py
xtlsapi/singbox_api/extensions_pb2_grpc.py
xtlsapi/singbox_api/stats_pb2.py
xtlsapi/singbox_api/stats_pb2_grpc.py
xtlsapi/singbox_api_services/__init__.py
xtlsapi/singbox_api_services/_base.py
xtlsapi/singbox_api_services/stats/__init__.py
xtlsapi/singbox_api_services/stats/get_client_download_traffic.py
xtlsapi/singbox_api_services/stats/get_client_upload_traffic.py
xtlsapi/singbox_api_services/stats/get_inbound_download_traffic.py
xtlsapi/singbox_api_services/stats/get_inbound_upload_traffic.py
xtlsapi/singbox_api_services/stats/get_statsquery.py
xtlsapi/singbox_api_services/stats/get_total_download_traffic.py
xtlsapi/singbox_api_services/stats/get_total_upload_traffic.py
xtlsapi/xray_api/__init__.py
xtlsapi/xray_api/app/__init__.py
xtlsapi-3.3.0.dist-info/LICENSE
xtlsapi-3.3.0.dist-info/METADATA
xtlsapi-3.3.0.dist-info/WHEEL
xtlsapi-3.3.0.dist-info/entry_points.txt
xtlsapi-3.3.0.dist-info/top_level.txt
xtlsapi-3.3.0.dist-info/RECORD
