Metadata-Version: 2.1
Name: xtlsapi
Version: 3.3.0
Summary: Awesome xtlsapi created by hiddify
Home-page: https://github.com/hiddify/xtlsapi/
Author: hiddify
License-File: LICENSE
Requires-Dist: grpcio
Requires-Dist: grpcio-tools<2.0.0
Requires-Dist: protobuf==5.28.3
Provides-Extra: test
Requires-Dist: pytest; extra == "test"
Requires-Dist: coverage; extra == "test"
Requires-Dist: flake8; extra == "test"
Requires-Dist: black; extra == "test"
Requires-Dist: isort; extra == "test"
Requires-Dist: pytest-cov; extra == "test"
Requires-Dist: codecov; extra == "test"
Requires-Dist: mypy; extra == "test"
Requires-Dist: gitchangelog; extra == "test"
Requires-Dist: mkdocs; extra == "test"
